<?xml version="1.0" encoding="UTF-8"?>
<databaseChangeLog xmlns="http://www.liquibase.org/xml/ns/dbchangelog"
                   xmlns:xsi="http://www.w3.org/2001/XMLSchema-instance"
                   xsi:schemaLocation="http://www.liquibase.org/xml/ns/dbchangelog
                                       http://www.liquibase.org/xml/ns/dbchangelog/dbchangelog-3.5.xsd">

    <changeSet author="exttno" id="1.3">
        <addColumn schemaName="conceptregistration"
                   tableName="conceptregistrations">
            <column name="omfang_tekst" type="varchar(255)"/>
        </addColumn>
        <addColumn schemaName="conceptregistration"
                   tableName="conceptregistrations">
            <column name="omfang_uri" type="varchar(255)"/>
        </addColumn>
        <addColumn schemaName="conceptregistration"
                   tableName="conceptregistrations">
            <column name="kontaktpunkt_harepost" type="varchar(255)"/>
        </addColumn>
        <addColumn schemaName="conceptregistration"
                   tableName="conceptregistrations">
            <column name="kontaktpunkt_hartelefon" type="varchar(255)"/>
        </addColumn>

        <dropColumn columnName="kontaktpunkt"
                    schemaName="conceptregistration"
                    tableName="conceptregistrations"/>
    </changeSet>

</databaseChangeLog>
